base4/__init__.py
base4/cli.py
base4-0.4.5.dist-info/LICENSE
base4-0.4.5.dist-info/METADATA
base4-0.4.5.dist-info/WHEEL
base4-0.4.5.dist-info/entry_points.txt
base4-0.4.5.dist-info/top_level.txt
base4-0.4.5.dist-info/RECORD
