Metadata-Version: 2.1
Name: base4
Version: 0.4.5
Summary: base4 Encoder/Decoder
Author: NasrPy
Requires-Python: >=3.6,<4.0
License-File: LICENSE
